{
  "stats": {
    "suites": 1,
    "tests": 2,
    "passes": 2,
    "pending": 0,
    "failures": 0,
    "start": "2023-12-18T19:17:37.334Z",
    "end": "2023-12-18T19:17:47.407Z",
    "duration": 10073
  },
  "tests": [
    {
      "title": "returns a year the Denver Broncos won the superbowl",
      "fullTitle": "superbowlWin(record) returns a year the Denver Broncos won the superbowl",
      "duration": 0,
      "currentRetry": 0,
      "err": {}
    },
    {
      "title": "returns undefined if the record has no win objects",
      "fullTitle": "superbowlWin(record) returns undefined if the record has no win objects",
      "duration": 0,
      "currentRetry": 0,
      "err": {}
    }
  ],
  "pending": [],
  "failures": [],
  "passes": [
    {
      "title": "returns a year the Denver Broncos won the superbowl",
      "fullTitle": "superbowlWin(record) returns a year the Denver Broncos won the superbowl",
      "duration": 0,
      "currentRetry": 0,
      "err": {}
    },
    {
      "title": "returns undefined if the record has no win objects",
      "fullTitle": "superbowlWin(record) returns undefined if the record has no win objects",
      "duration": 0,
      "currentRetry": 0,
      "err": {}
    }
  ]
}